source_partnerstack/__init__.py
source_partnerstack/components.py
source_partnerstack/manifest.yaml
source_partnerstack/run.py
source_partnerstack/schemas/customers.json
source_partnerstack/schemas/deals.json
source_partnerstack/schemas/groups.json
source_partnerstack/schemas/leads.json
source_partnerstack/schemas/partnerships.json
source_partnerstack/schemas/rewards.json
source_partnerstack/schemas/transactions.json
source_partnerstack/source.py
source_partnerstack/spec.yaml
airbyte_source_partnerstack-0.2.8.dist-info/METADATA
airbyte_source_partnerstack-0.2.8.dist-info/WHEEL
airbyte_source_partnerstack-0.2.8.dist-info/entry_points.txt
airbyte_source_partnerstack-0.2.8.dist-info/RECORD
